qedtool/__init__.py
qedtool/qed.py
qedtool/qinfo.py
qedtool/relativity.py
qedtool/standard_processes.py
qedtool-0.1.2.dist-info/METADATA
qedtool-0.1.2.dist-info/WHEEL
qedtool-0.1.2.dist-info/licenses/LICENSE
qedtool-0.1.2.dist-info/RECORD
