Metadata-Version: 2.4
Name: qedtool
Version: 0.1.2
Summary: A tool for numerical quantum information calculations in tree-level quantum electrodynamics (QED).
Project-URL: Homepage, https://github.com/jsmeets2k/qedtool
Author-email: Jesse Smeets <j.smeets.physics@gmail.com>, Preslav Asenov <preslav.asenov.20@ucl.ac.uk>, Alessio Serafini <serale@theory.phys.ucl.ac.uk>
License-Expression: MIT
License-File: LICENSE
Keywords: numpy,particle physics,quantum information,scattering
Classifier: Operating System :: OS Independent
Classifier: Programming Language :: Python :: 3.10
Requires-Python: >=3.10
Requires-Dist: numpy>=1.26.4
Requires-Dist: transforms3d>=0.4.2
